Metadata-Version: 2.1
Name: tribolium-clustering
Version: 0.2.5
Summary: A library for image ananalysis and data analysis of Tribolium embryos
Home-page: https://github.com/Cryaaa/tribolium-clustering
Author: Ryan Savill
Author-email: ryan_george.savill@mailbox.tu-dresden.de
Project-URL: Bug Reports, https://github.com/Cryaaa/tribolium-clustering/issues
Project-URL: Source, https://github.com/Cryaaa/tribolium-clustering
Keywords: image,analysis,development,tribolium,clustering
Classifier: Development Status :: 3 - Alpha
Classifier: License :: OSI Approved :: BSD License
Classifier: Programming Language :: Python :: 3.7
Classifier: Programming Language :: Python :: 3.8
Classifier: Programming Language :: Python :: 3 :: Only
Requires-Python: >=3.7, <3.10
License-File: LICENSE
Requires-Dist: seaborn
Requires-Dist: umap-learn
Requires-Dist: hdbscan
Requires-Dist: numpy
Requires-Dist: pyopencl
Requires-Dist: scikit-image
Requires-Dist: scikit-learn
Requires-Dist: pyclesperanto-prototype
Requires-Dist: pandas
Requires-Dist: pywebview
Requires-Dist: PySimpleGUI
Requires-Dist: pythonnet (==3.0.0a2)
Requires-Dist: vispy
